poetry_packaging_poc/__init__.py
poetry_packaging_poc/console.py
poetry_packaging_poc-0.4.0.dist-info/entry_points.txt
poetry_packaging_poc-0.4.0.dist-info/LICENSE
poetry_packaging_poc-0.4.0.dist-info/WHEEL
poetry_packaging_poc-0.4.0.dist-info/METADATA
poetry_packaging_poc-0.4.0.dist-info/RECORD
